zoho_projects_sdk/__init__.py
zoho_projects_sdk/_version.py
zoho_projects_sdk/auth.py
zoho_projects_sdk/client.py
zoho_projects_sdk/config.py
zoho_projects_sdk/exceptions.py
zoho_projects_sdk/http_client.py
zoho_projects_sdk/api/__init__.py
zoho_projects_sdk/api/attachments.py
zoho_projects_sdk/api/baselines.py
zoho_projects_sdk/api/business_hours.py
zoho_projects_sdk/api/clients.py
zoho_projects_sdk/api/comments.py
zoho_projects_sdk/api/contacts.py
zoho_projects_sdk/api/events.py
zoho_projects_sdk/api/issues.py
zoho_projects_sdk/api/milestones.py
zoho_projects_sdk/api/phases.py
zoho_projects_sdk/api/portals.py
zoho_projects_sdk/api/projects.py
zoho_projects_sdk/api/roles.py
zoho_projects_sdk/api/tags.py
zoho_projects_sdk/api/tasklists.py
zoho_projects_sdk/api/tasks.py
zoho_projects_sdk/api/timelogs.py
zoho_projects_sdk/api/users.py
zoho_projects_sdk/models/__init__.py
zoho_projects_sdk/models/attachment_models.py
zoho_projects_sdk/models/baseline_models.py
zoho_projects_sdk/models/business_hours_models.py
zoho_projects_sdk/models/client_models.py
zoho_projects_sdk/models/comment_models.py
zoho_projects_sdk/models/contact_models.py
zoho_projects_sdk/models/event_models.py
zoho_projects_sdk/models/issue_models.py
zoho_projects_sdk/models/milestone_models.py
zoho_projects_sdk/models/phase_models.py
zoho_projects_sdk/models/portal_models.py
zoho_projects_sdk/models/project_models.py
zoho_projects_sdk/models/role_models.py
zoho_projects_sdk/models/tag_models.py
zoho_projects_sdk/models/task_models.py
zoho_projects_sdk/models/tasklist_models.py
zoho_projects_sdk/models/timelog_models.py
zoho_projects_sdk/models/user_models.py
zoho_projects_sdk/utils/__init__.py
zoho_projects_sdk/utils/logger.py
zoho_projects_sdk-0.1.11.dist-info/licenses/LICENSE
zoho_projects_sdk-0.1.11.dist-info/METADATA
zoho_projects_sdk-0.1.11.dist-info/WHEEL
zoho_projects_sdk-0.1.11.dist-info/top_level.txt
zoho_projects_sdk-0.1.11.dist-info/RECORD
