Metadata-Version: 2.4
Name: zoho-projects-sdk
Version: 0.1.11
Summary: A modern, asynchronous, and type-safe Python SDK for the Zoho Projects API V3.
Author-email: Carlos Paiva <2202731+carlospaiva@users.noreply.github.com>
Project-URL: Bug Tracker, https://github.com/carlospaiva/zoho-projects-sdk/issues
Project-URL: Homepage, https://github.com/carlospaiva/zoho-projects-sdk
Classifier: Programming Language :: Python :: 3
Classifier: Programming Language :: Python :: 3.9
Classifier: Programming Language :: Python :: 3.10
Classifier: Programming Language :: Python :: 3.11
Classifier: Programming Language :: Python :: 3.12
Classifier: Programming Language :: Python :: 3.13
Classifier: License :: OSI Approved :: MIT License
Classifier: Operating System :: OS Independent
Classifier: Intended Audience :: Developers
Classifier: Topic :: Software Development :: Libraries :: Python Modules
Classifier: Framework :: AsyncIO
Requires-Python: >=3.9
License-File: LICENSE
Requires-Dist: pydantic>=2.0
Requires-Dist: httpx>=0.25.0
Requires-Dist: python-dotenv>=1.0.0
Requires-Dist: tenacity>=8.2.0
Provides-Extra: dev
Requires-Dist: uv>=0.0.0; extra == "dev"
Requires-Dist: mypy>=1.5.1; extra == "dev"
Requires-Dist: flake8>=6.1.0; extra == "dev"
Requires-Dist: isort>=5.12.0; extra == "dev"
Requires-Dist: black>=23.9.1; extra == "dev"
Requires-Dist: pylint>=3.0.0; extra == "dev"
Requires-Dist: pytest>=7.4.2; extra == "dev"
Requires-Dist: pytest-cov>=4.1.0; extra == "dev"
Requires-Dist: respx>=0.2; extra == "dev"
Requires-Dist: pytest-asyncio>=0.21.0; extra == "dev"
Requires-Dist: build>=1.0.0; extra == "dev"
Requires-Dist: twine>=4.0.2; extra == "dev"
Dynamic: license-file
